{
  "name": "Necaxa",
  "last_match": {
    "vs": "Guadalajara Chivas",
    "date": "2025-09-23",
    "time": "20:07",
    "home": false,
    "score": "3 - 1",
    "result": "L"
  },
  "record": {
    "total": {
      "games_played": 327,
      "wins": 103,
      "draws": 95,
      "losses": 129,
      "goals_for": 412,
      "goals_against": 450,
      "goal_difference": -38,
      "win_rate": 31.5
    },
    "home": {
      "games_played": 162,
      "wins": 58,
      "draws": 53,
      "losses": 51,
      "goals_for": 218,
      "goals_against": 203,
      "goal_difference": 15,
      "win_rate": 35.8
    },
    "away": {
      "games_played": 165,
      "wins": 45,
      "draws": 42,
      "losses": 78,
      "goals_for": 194,
      "goals_against": 247,
      "goal_difference": -53,
      "win_rate": 27.27
    }
  },
  "form": [
    "L",
    "L",
    "D",
    "W",
    "L"
  ],
  "match_history": [
    {
      "date": "2024-10-05",
      "goals_for": 0,
      "goals_against": 3,
      "result": "L"
    },
    {
      "date": "2024-10-18",
      "goals_for": 1,
      "goals_against": 2,
      "result": "L"
    },
    {
      "date": "2024-10-22",
      "goals_for": 2,
      "goals_against": 3,
      "result": "L"
    },
    {
      "date": "2024-10-27",
      "goals_for": 1,
      "goals_against": 3,
      "result": "L"
    },
    {
      "date": "2024-11-02",
      "goals_for": 2,
      "goals_against": 6,
      "result": "L"
    },
    {
      "date": "2024-11-06",
      "goals_for": 1,
      "goals_against": 1,
      "result": "T"
    },
    {
      "date": "2024-11-10",
      "goals_for": 0,
      "goals_against": 0,
      "result": "T"
    },
    {
      "date": "2025-01-12",
      "goals_for": 1,
      "goals_against": 2,
      "result": "L"
    },
    {
      "date": "2025-01-17",
      "goals_for": 3,
      "goals_against": 2,
      "result": "W"
    },
    {
      "date": "2025-01-24",
      "goals_for": 3,
      "goals_against": 0,
      "result": "W"
    },
    {
      "date": "2025-01-28",
      "goals_for": 1,
      "goals_against": 3,
      "result": "L"
    },
    {
      "date": "2025-02-01",
      "goals_for": 0,
      "goals_against": 1,
      "result": "L"
    },
    {
      "date": "2025-02-07",
      "goals_for": 3,
      "goals_against": 2,
      "result": "W"
    },
    {
      "date": "2025-02-14",
      "goals_for": 3,
      "goals_against": 2,
      "result": "W"
    },
    {
      "date": "2025-02-18",
      "goals_for": 4,
      "goals_against": 0,
      "result": "W"
    },
    {
      "date": "2025-02-21",
      "goals_for": 3,
      "goals_against": 1,
      "result": "W"
    },
    {
      "date": "2025-03-01",
      "goals_for": 1,
      "goals_against": 2,
      "result": "L"
    },
    {
      "date": "2025-03-08",
      "goals_for": 2,
      "goals_against": 5,
      "result": "L"
    },
    {
      "date": "2025-03-14",
      "goals_for": 2,
      "goals_against": 1,
      "result": "W"
    },
    {
      "date": "2025-03-28",
      "goals_for": 2,
      "goals_against": 0,
      "result": "W"
    },
    {
      "date": "2025-04-04",
      "goals_for": 2,
      "goals_against": 1,
      "result": "W"
    },
    {
      "date": "2025-04-11",
      "goals_for": 3,
      "goals_against": 5,
      "result": "L"
    },
    {
      "date": "2025-04-15",
      "goals_for": 2,
      "goals_against": 2,
      "result": "T"
    },
    {
      "date": "2025-04-18",
      "goals_for": 1,
      "goals_against": 0,
      "result": "W"
    },
    {
      "date": "2025-05-08",
      "goals_for": 0,
      "goals_against": 0,
      "result": "T"
    },
    {
      "date": "2025-05-11",
      "goals_for": 2,
      "goals_against": 2,
      "result": "T"
    },
    {
      "date": "2025-07-12",
      "goals_for": 1,
      "goals_against": 3,
      "result": "L"
    },
    {
      "date": "2025-07-18",
      "goals_for": 3,
      "goals_against": 1,
      "result": "W"
    },
    {
      "date": "2025-07-26",
      "goals_for": 1,
      "goals_against": 1,
      "result": "T"
    },
    {
      "date": "2025-08-10",
      "goals_for": 1,
      "goals_against": 1,
      "result": "T"
    },
    {
      "date": "2025-08-15",
      "goals_for": 0,
      "goals_against": 1,
      "result": "L"
    },
    {
      "date": "2025-08-23",
      "goals_for": 0,
      "goals_against": 3,
      "result": "L"
    },
    {
      "date": "2025-08-31",
      "goals_for": 0,
      "goals_against": 3,
      "result": "L"
    },
    {
      "date": "2025-09-12",
      "goals_for": 1,
      "goals_against": 1,
      "result": "T"
    },
    {
      "date": "2025-09-19",
      "goals_for": 1,
      "goals_against": 0,
      "result": "W"
    },
    {
      "date": "2025-09-23",
      "goals_for": 1,
      "goals_against": 3,
      "result": "L"
    }
  ],
  "last_match_betting": {
    "prob_home": 51.85220914528266,
    "prob_draw": 25.718695736060198,
    "prob_away": 22.429095118657152,
    "max_home": 2.05,
    "max_draw": 3.7,
    "max_away": 3.7,
    "avg_home": 1.95,
    "avg_draw": 3.54,
    "avg_away": 3.45,
    "bfe_home": 2.1,
    "bfe_draw": 3.65,
    "bfe_away": 3.95
  }
}