{
  "name": "Pachuca",
  "last_match": {
    "vs": "Mazatlan FC",
    "date": "2025-07-26",
    "time": "18:00",
    "home": true,
    "score": "1 - 0",
    "result": "W"
  },
  "record": {
    "total": {
      "games_played": 489,
      "wins": 197,
      "draws": 132,
      "losses": 160,
      "goals_for": 716,
      "goals_against": 621,
      "goal_difference": 95,
      "win_rate": 40.29
    },
    "home": {
      "games_played": 246,
      "wins": 123,
      "draws": 68,
      "losses": 55,
      "goals_for": 402,
      "goals_against": 254,
      "goal_difference": 148,
      "win_rate": 50.0
    },
    "away": {
      "games_played": 243,
      "wins": 74,
      "draws": 64,
      "losses": 105,
      "goals_for": 314,
      "goals_against": 367,
      "goal_difference": -53,
      "win_rate": 30.45
    }
  },
  "form": [
    "D",
    "L",
    "W",
    "W",
    "W"
  ],
  "match_history": [
    {
      "date": "2024-08-23",
      "goals_for": 0,
      "goals_against": 3,
      "result": "L"
    },
    {
      "date": "2024-08-31",
      "goals_for": 1,
      "goals_against": 1,
      "result": "T"
    },
    {
      "date": "2024-09-13",
      "goals_for": 0,
      "goals_against": 2,
      "result": "L"
    },
    {
      "date": "2024-09-17",
      "goals_for": 2,
      "goals_against": 2,
      "result": "T"
    },
    {
      "date": "2024-09-20",
      "goals_for": 3,
      "goals_against": 2,
      "result": "W"
    },
    {
      "date": "2024-09-28",
      "goals_for": 2,
      "goals_against": 4,
      "result": "L"
    },
    {
      "date": "2024-10-04",
      "goals_for": 1,
      "goals_against": 2,
      "result": "L"
    },
    {
      "date": "2024-10-19",
      "goals_for": 0,
      "goals_against": 2,
      "result": "L"
    },
    {
      "date": "2024-10-22",
      "goals_for": 1,
      "goals_against": 1,
      "result": "T"
    },
    {
      "date": "2024-10-26",
      "goals_for": 1,
      "goals_against": 2,
      "result": "L"
    },
    {
      "date": "2024-11-02",
      "goals_for": 6,
      "goals_against": 2,
      "result": "W"
    },
    {
      "date": "2024-11-06",
      "goals_for": 1,
      "goals_against": 2,
      "result": "L"
    },
    {
      "date": "2024-11-09",
      "goals_for": 0,
      "goals_against": 1,
      "result": "L"
    },
    {
      "date": "2025-01-20",
      "goals_for": 2,
      "goals_against": 1,
      "result": "W"
    },
    {
      "date": "2025-01-25",
      "goals_for": 3,
      "goals_against": 2,
      "result": "W"
    },
    {
      "date": "2025-01-29",
      "goals_for": 1,
      "goals_against": 0,
      "result": "W"
    },
    {
      "date": "2025-02-01",
      "goals_for": 0,
      "goals_against": 0,
      "result": "T"
    },
    {
      "date": "2025-02-05",
      "goals_for": 1,
      "goals_against": 2,
      "result": "L"
    },
    {
      "date": "2025-02-08",
      "goals_for": 1,
      "goals_against": 2,
      "result": "L"
    },
    {
      "date": "2025-02-16",
      "goals_for": 2,
      "goals_against": 1,
      "result": "W"
    },
    {
      "date": "2025-02-22",
      "goals_for": 1,
      "goals_against": 2,
      "result": "L"
    },
    {
      "date": "2025-02-26",
      "goals_for": 2,
      "goals_against": 1,
      "result": "W"
    },
    {
      "date": "2025-03-01",
      "goals_for": 2,
      "goals_against": 2,
      "result": "T"
    },
    {
      "date": "2025-03-08",
      "goals_for": 1,
      "goals_against": 1,
      "result": "T"
    },
    {
      "date": "2025-03-16",
      "goals_for": 4,
      "goals_against": 1,
      "result": "W"
    },
    {
      "date": "2025-03-29",
      "goals_for": 2,
      "goals_against": 3,
      "result": "L"
    },
    {
      "date": "2025-04-05",
      "goals_for": 1,
      "goals_against": 0,
      "result": "W"
    },
    {
      "date": "2025-04-11",
      "goals_for": 5,
      "goals_against": 3,
      "result": "W"
    },
    {
      "date": "2025-04-15",
      "goals_for": 0,
      "goals_against": 0,
      "result": "T"
    },
    {
      "date": "2025-04-20",
      "goals_for": 1,
      "goals_against": 2,
      "result": "L"
    },
    {
      "date": "2025-04-27",
      "goals_for": 2,
      "goals_against": 1,
      "result": "W"
    },
    {
      "date": "2025-05-07",
      "goals_for": 0,
      "goals_against": 0,
      "result": "T"
    },
    {
      "date": "2025-05-10",
      "goals_for": 0,
      "goals_against": 2,
      "result": "L"
    },
    {
      "date": "2025-07-13",
      "goals_for": 3,
      "goals_against": 0,
      "result": "W"
    },
    {
      "date": "2025-07-20",
      "goals_for": 3,
      "goals_against": 2,
      "result": "W"
    },
    {
      "date": "2025-07-26",
      "goals_for": 1,
      "goals_against": 0,
      "result": "W"
    }
  ],
  "last_match_betting": {
    "prob_home": 68.96919233971691,
    "prob_draw": 19.467110741049126,
    "prob_away": 11.563696919233973,
    "max_home": 1.43,
    "max_draw": 4.96,
    "max_away": 9.0,
    "avg_home": 1.37,
    "avg_draw": 4.58,
    "avg_away": 7.54,
    "bfe_home": 1.42,
    "bfe_draw": 5.1,
    "bfe_away": 9.6
  }
}