{
  "name": "Santos Laguna",
  "last_match": {
    "vs": "UNAM Pumas",
    "date": "2026-01-30",
    "time": "21:00",
    "home": false,
    "score": "4 - 0",
    "result": "L"
  },
  "record": {
    "total": {
      "games_played": 507,
      "wins": 182,
      "draws": 140,
      "losses": 185,
      "goals_for": 724,
      "goals_against": 729,
      "goal_difference": -5,
      "win_rate": 35.9
    },
    "home": {
      "games_played": 255,
      "wins": 129,
      "draws": 63,
      "losses": 63,
      "goals_for": 428,
      "goals_against": 308,
      "goal_difference": 120,
      "win_rate": 50.59
    },
    "away": {
      "games_played": 252,
      "wins": 53,
      "draws": 77,
      "losses": 122,
      "goals_for": 296,
      "goals_against": 421,
      "goal_difference": -125,
      "win_rate": 21.03
    }
  },
  "form": [
    "W",
    "L",
    "L",
    "D",
    "L"
  ],
  "match_history": [
    {
      "date": "2025-02-14",
      "goals_for": 1,
      "goals_against": 1,
      "result": "T"
    },
    {
      "date": "2025-02-19",
      "goals_for": 0,
      "goals_against": 1,
      "result": "L"
    },
    {
      "date": "2025-02-23",
      "goals_for": 2,
      "goals_against": 0,
      "result": "W"
    },
    {
      "date": "2025-03-02",
      "goals_for": 2,
      "goals_against": 4,
      "result": "L"
    },
    {
      "date": "2025-03-09",
      "goals_for": 2,
      "goals_against": 1,
      "result": "W"
    },
    {
      "date": "2025-03-15",
      "goals_for": 0,
      "goals_against": 3,
      "result": "L"
    },
    {
      "date": "2025-03-30",
      "goals_for": 2,
      "goals_against": 3,
      "result": "L"
    },
    {
      "date": "2025-04-06",
      "goals_for": 1,
      "goals_against": 2,
      "result": "L"
    },
    {
      "date": "2025-04-13",
      "goals_for": 1,
      "goals_against": 2,
      "result": "L"
    },
    {
      "date": "2025-04-16",
      "goals_for": 0,
      "goals_against": 2,
      "result": "L"
    },
    {
      "date": "2025-04-20",
      "goals_for": 0,
      "goals_against": 4,
      "result": "L"
    },
    {
      "date": "2025-07-12",
      "goals_for": 3,
      "goals_against": 0,
      "result": "W"
    },
    {
      "date": "2025-07-16",
      "goals_for": 2,
      "goals_against": 4,
      "result": "L"
    },
    {
      "date": "2025-07-25",
      "goals_for": 0,
      "goals_against": 1,
      "result": "L"
    },
    {
      "date": "2025-08-10",
      "goals_for": 1,
      "goals_against": 0,
      "result": "W"
    },
    {
      "date": "2025-08-16",
      "goals_for": 2,
      "goals_against": 3,
      "result": "L"
    },
    {
      "date": "2025-08-22",
      "goals_for": 1,
      "goals_against": 2,
      "result": "L"
    },
    {
      "date": "2025-08-30",
      "goals_for": 0,
      "goals_against": 1,
      "result": "L"
    },
    {
      "date": "2025-09-13",
      "goals_for": 2,
      "goals_against": 2,
      "result": "T"
    },
    {
      "date": "2025-09-21",
      "goals_for": 1,
      "goals_against": 4,
      "result": "L"
    },
    {
      "date": "2025-09-24",
      "goals_for": 1,
      "goals_against": 0,
      "result": "W"
    },
    {
      "date": "2025-09-27",
      "goals_for": 0,
      "goals_against": 1,
      "result": "L"
    },
    {
      "date": "2025-10-04",
      "goals_for": 0,
      "goals_against": 3,
      "result": "L"
    },
    {
      "date": "2025-10-18",
      "goals_for": 2,
      "goals_against": 0,
      "result": "W"
    },
    {
      "date": "2025-10-21",
      "goals_for": 2,
      "goals_against": 2,
      "result": "T"
    },
    {
      "date": "2025-10-26",
      "goals_for": 3,
      "goals_against": 1,
      "result": "W"
    },
    {
      "date": "2025-10-31",
      "goals_for": 1,
      "goals_against": 4,
      "result": "L"
    },
    {
      "date": "2025-11-09",
      "goals_for": 1,
      "goals_against": 0,
      "result": "W"
    },
    {
      "date": "2026-01-10",
      "goals_for": 1,
      "goals_against": 3,
      "result": "L"
    },
    {
      "date": "2026-01-14",
      "goals_for": 1,
      "goals_against": 3,
      "result": "L"
    },
    {
      "date": "2026-01-18",
      "goals_for": 2,
      "goals_against": 2,
      "result": "T"
    },
    {
      "date": "2026-01-30",
      "goals_for": 0,
      "goals_against": 4,
      "result": "L"
    }
  ],
  "last_match_betting": {
    "prob_home": NaN,
    "prob_draw": NaN,
    "prob_away": NaN,
    "max_home": 1.56,
    "max_draw": 4.5,
    "max_away": 5.8,
    "avg_home": 1.51,
    "avg_draw": 4.27,
    "avg_away": 5.49,
    "bfe_home": 1.56,
    "bfe_draw": 4.8,
    "bfe_away": 6.2
  }
}